README.md
setup.py
sqlalchemy_mixins/__init__.py
sqlalchemy_mixins/activerecord.py
sqlalchemy_mixins/eagerload.py
sqlalchemy_mixins/inspection.py
sqlalchemy_mixins/repr.py
sqlalchemy_mixins/serialize.py
sqlalchemy_mixins/smartquery.py
sqlalchemy_mixins/utils.py
sqlalchemy_mixins_for_starlette.egg-info/PKG-INFO
sqlalchemy_mixins_for_starlette.egg-info/SOURCES.txt
sqlalchemy_mixins_for_starlette.egg-info/dependency_links.txt
sqlalchemy_mixins_for_starlette.egg-info/not-zip-safe
sqlalchemy_mixins_for_starlette.egg-info/requires.txt
sqlalchemy_mixins_for_starlette.egg-info/top_level.txt