Metadata-Version: 1.1
Name: sqlalchemy-mixins-for-starlette
Version: 1.0
Summary: Active Record, Django-like queries, nested eager load and beauty __repr__ for SQLAlchemy
Home-page: https://github.com/scil/sqlalchemy-mixins-for-starlette
Author: Alexander Litvinenko
Author-email: litvinenko1706@gmail.com
License: MIT
Download-URL: https://github.com/scil/sqlalchemy-mixins-for-starlette/archive/master.tar.gz
Keywords: sqlalchemy,active record,activerecord,orm,django-like,django,eager load,eagerload,repr,__repr__,mysql,postgresql,pymysql,sqlite
Platform: any
Classifier: Development Status :: 4 - Beta
Classifier: Environment :: Web Environment
Classifier: Intended Audience :: Developers
Classifier: License :: OSI Approved :: MIT License
Classifier: Programming Language :: Python :: 3.7
Classifier: Programming Language :: Python :: 3.8
Classifier: Programming Language :: Python :: Implementation :: CPython
Classifier: Topic :: Database
